{
  "model": "kimi-k2-5",
  "parameters": {
    "vail_only": true
  },
  "providers": {
    "baseten": {
      "vail": {
        "endpoint": "kimi-k2.5-baseten-chat",
        "divergence_ratio": 6.999454147056997,
        "date": "2026-03-15",
        "comparison_providers": [
          "bedrock",
          "deepinfra",
          "fireworks",
          "novita",
          "parasail",
          "together"
        ]
      }
    },
    "bedrock": {
      "vail": {
        "endpoint": "kimi-k2.5-bedrock-chat",
        "divergence_ratio": 4.50111807986779,
        "date": "2026-03-15",
        "comparison_providers": [
          "baseten",
          "deepinfra",
          "fireworks",
          "novita",
          "parasail",
          "together"
        ]
      }
    },
    "deepinfra": {
      "vail": {
        "endpoint": "kimi-k2.5-deepinfra-chat",
        "divergence_ratio": 1,
        "date": "2026-03-15",
        "comparison_providers": [
          "baseten",
          "bedrock",
          "fireworks",
          "novita",
          "parasail",
          "together"
        ]
      }
    },
    "fireworks": {
      "vail": {
        "endpoint": "kimi-k2.5-fireworks-chat",
        "divergence_ratio": 0.8270525317317539,
        "date": "2026-03-15",
        "comparison_providers": [
          "baseten",
          "bedrock",
          "deepinfra",
          "novita",
          "parasail",
          "together"
        ]
      }
    },
    "novita": {
      "vail": {
        "endpoint": "kimi-k2.5-novita-chat",
        "divergence_ratio": 0.8435050707048661,
        "date": "2026-03-15",
        "comparison_providers": [
          "baseten",
          "bedrock",
          "deepinfra",
          "fireworks",
          "parasail",
          "together"
        ]
      }
    },
    "parasail": {
      "vail": {
        "endpoint": "kimi-k2.5-parasail-chat",
        "divergence_ratio": 0.8583883155144856,
        "date": "2026-03-15",
        "comparison_providers": [
          "baseten",
          "bedrock",
          "deepinfra",
          "fireworks",
          "novita",
          "together"
        ]
      }
    },
    "together": {
      "vail": {
        "endpoint": "kimi-k2.5-together-chat",
        "divergence_ratio": 1.2096871414249422,
        "date": "2026-03-15",
        "comparison_providers": [
          "baseten",
          "bedrock",
          "deepinfra",
          "fireworks",
          "novita",
          "parasail"
        ]
      }
    }
  }
}
